ci_buildbot/__init__.py
ci_buildbot/cli.py
ci_buildbot/exc.py
ci_buildbot/settings.py
ci_buildbot/typedefs.py
ci_buildbot/context_processors/__init__.py
ci_buildbot/context_processors/base.py
ci_buildbot/context_processors/codebuild.py
ci_buildbot/context_processors/deployfish.py
ci_buildbot/context_processors/docker.py
ci_buildbot/context_processors/generic.py
ci_buildbot/context_processors/git.py
ci_buildbot/context_processors/project.py
ci_buildbot/context_processors/unittest.py
ci_buildbot/messages/__init__.py
ci_buildbot/messages/archive.py
ci_buildbot/messages/base.py
ci_buildbot/messages/deployfish.py
ci_buildbot/messages/deployfish_tasks.py
ci_buildbot/messages/docker.py
ci_buildbot/messages/docs.py
ci_buildbot/messages/general.py
ci_buildbot/messages/unittests.py
ci_buildbot/templates/archive.tpl
ci_buildbot/templates/deploy_failed.tpl
ci_buildbot/templates/deploy_start.tpl
ci_buildbot/templates/deploy_success.tpl
ci_buildbot/templates/deploy_tasks_failed.tpl
ci_buildbot/templates/deploy_tasks_start.tpl
ci_buildbot/templates/deploy_tasks_success.tpl
ci_buildbot/templates/docker_failed.tpl
ci_buildbot/templates/docker_start.tpl
ci_buildbot/templates/docker_success.tpl
ci_buildbot/templates/docs_failed.tpl
ci_buildbot/templates/docs_start.tpl
ci_buildbot/templates/docs_success.tpl
ci_buildbot/templates/general_failed.tpl
ci_buildbot/templates/general_start.tpl
ci_buildbot/templates/general_success.tpl
ci_buildbot/templates/unittests_failed.tpl
ci_buildbot/templates/unittests_start.tpl
ci_buildbot/templates/unittests_success.tpl
ci_buildbot-0.11.3.dist-info/METADATA
ci_buildbot-0.11.3.dist-info/WHEEL
ci_buildbot-0.11.3.dist-info/entry_points.txt
ci_buildbot-0.11.3.dist-info/top_level.txt
ci_buildbot-0.11.3.dist-info/RECORD
