Metadata-Version: 2.1
Name: ci-buildbot
Version: 0.11.3
Summary: Slack client for reporting on CodePipeline runs
Author-email: Caltech IMSS ADS <imss-ads-staff@caltech.edu>
Maintainer-email: Christopher Malek <cmalek@caltech.edu>, Glenn Bach <glenn@caltech.edu>
Project-URL: Repository, https://github.com/caltechads/ci-buildbot
Project-URL: Issues, https://github.com/caltechads/ci-buildbot/issues
Keywords: aws,ecs,docker,devops
Classifier: Development Status :: 5 - Production/Stable
Classifier: Environment :: Console
Classifier: Intended Audience :: Developers
Classifier: Intended Audience :: System Administrators
Classifier: Operating System :: OS Independent
Classifier: Programming Language :: Python
Classifier: Programming Language :: Python :: 3
Classifier: Programming Language :: Python :: 3.9
Classifier: Programming Language :: Python :: 3.10
Classifier: Programming Language :: Python :: 3.11
Classifier: Programming Language :: Python :: 3.12
Classifier: Topic :: Software Development :: Build Tools
Requires-Python: >=3.9
Requires-Dist: slackclient>=2.9.4
Requires-Dist: docker>=7.1.0
Requires-Dist: gitpython>=3.1.43
Requires-Dist: giturlparse>=0.11.3
Requires-Dist: click>=8.0
Requires-Dist: jinja2>=2.11.1
Requires-Dist: pydantic>=2.9.1
Requires-Dist: pydantic-settings>=2.5.2
Requires-Dist: pytz==2024.1
Requires-Dist: sh==1.13.1
Requires-Dist: toml==0.10.2
